protlib_designer/__init__.py
protlib_designer/_version.py
protlib_designer/dataloader.py
protlib_designer/solution_manager.py
protlib_designer/utils.py
protlib_designer-2.0.1.dev13.dist-info/licenses/LICENSE
protlib_designer-2.0.1.dev13.dist-info/licenses/NOTICE
scripts/__init__.py
scripts/run_ifold_scorer.py
scripts/run_plm_scorer.py
scripts/run_protlib_designer.py
tests/__init__.py
tests/test_run_protlib_designer.py
protlib_designer-2.0.1.dev13.dist-info/METADATA
protlib_designer-2.0.1.dev13.dist-info/WHEEL
protlib_designer-2.0.1.dev13.dist-info/entry_points.txt
protlib_designer-2.0.1.dev13.dist-info/top_level.txt
protlib_designer-2.0.1.dev13.dist-info/RECORD
