Metadata-Version: 2.4
Name: protlib_designer
Version: 2.0.1.dev13
Summary: Integer Linear Programming for Protein Library Design
Home-page: https://github.com/LLNL/protlib-designer
Author: Mikel Landajuela
Author-email: landajuelala1@llnl.gov
License: MIT
Keywords: protein design,ILP,bioinformatics
Requires-Python: >=3.10
License-File: LICENSE
License-File: NOTICE
Requires-Dist: click
Requires-Dist: numpy==1.26.4
Requires-Dist: pandas
Requires-Dist: pulp
Provides-Extra: dev
Requires-Dist: black==22.8.0; extra == "dev"
Requires-Dist: flake8==5.0.4; extra == "dev"
Requires-Dist: pytest; extra == "dev"
Requires-Dist: coverage; extra == "dev"
Provides-Extra: plm
Requires-Dist: torch; extra == "plm"
Requires-Dist: transformers; extra == "plm"
Provides-Extra: ifold
Requires-Dist: torch; extra == "ifold"
Requires-Dist: proteinmpnn; extra == "ifold"
Provides-Extra: all
Requires-Dist: black==22.8.0; extra == "all"
Requires-Dist: flake8==5.0.4; extra == "all"
Requires-Dist: pytest; extra == "all"
Requires-Dist: coverage; extra == "all"
Requires-Dist: torch; extra == "all"
Requires-Dist: transformers; extra == "all"
Requires-Dist: torch; extra == "all"
Requires-Dist: proteinmpnn; extra == "all"
Dynamic: license-file
